hcat/__init__.py
hcat/__main__.py
hcat/license.py
hcat/main.py
hcat/todo.py
hcat/backends/__init__.py
hcat/backends/backend.py
hcat/backends/convnext.py
hcat/cabr/EPL_parser.py
hcat/cabr/EPL_saver.py
hcat/cabr/HDF5_parser.py
hcat/cabr/NCARAR_parser.py
hcat/cabr/__init__.py
hcat/cabr/abr_dataloader.py
hcat/cabr/abr_evaluator.py
hcat/cabr/abr_predictor_model.py
hcat/cabr/abr_store.py
hcat/cabr/abr_trainer.py
hcat/cabr/abr_transforms.py
hcat/cabr/cabr_lisence.py
hcat/cabr/kirupa_threshold.py
hcat/cabr/peak_finder.py
hcat/cabr/train_parser.py
hcat/config/__init__.py
hcat/config/config.py
hcat/config/valid.py
hcat/gui/__init__.py
hcat/gui/abr_analyzer.py
hcat/gui/abr_batch_table_viewer_widget.py
hcat/gui/abr_batch_widget.py
hcat/gui/abr_viewer.py
hcat/gui/analyze_widget.py
hcat/gui/annotate_widget.py
hcat/gui/canvas.py
hcat/gui/cell_sidebar_info.py
hcat/gui/colors.py
hcat/gui/edit_cell_params_widget.py
hcat/gui/eval_widget.py
hcat/gui/footer_widget.py
hcat/gui/histogram_widget.py
hcat/gui/image_adjust_widget.py
hcat/gui/image_import_widget.py
hcat/gui/key_input.py
hcat/gui/piece_sidebar_info.py
hcat/gui/piece_tree_viewer.py
hcat/gui/render_hint_widget.py
hcat/gui/render_style_widget.py
hcat/gui/resources.py
hcat/gui/train_config_widget.py
hcat/gui/tree_widget_item.py
hcat/lib/__init__.py
hcat/lib/adjust.py
hcat/lib/analyze.py
hcat/lib/animal.py
hcat/lib/authentication.py
hcat/lib/export.py
hcat/lib/frequency.py
hcat/lib/histogram.py
hcat/lib/importfromxml.py
hcat/lib/io.py
hcat/lib/multiprocess.py
hcat/lib/roi.py
hcat/lib/types.py
hcat/lib/utils.py
hcat/state/__init__.py
hcat/state/abr_waveform_dataclass.py
hcat/state/cell.py
hcat/state/cochlea.py
hcat/state/gui_state.py
hcat/state/item.py
hcat/state/load.py
hcat/state/piece.py
hcat/state/save.py
hcat/state/synapse.py
hcat/train/__init__.py
hcat/train/dataloader.py
hcat/train/default_engine.py
hcat/train/marketplace.py
hcat/train/merged_transform.py
hcat/train/test.py
hcat/train/widgets.py
hcat/utils/__init__.py
hcat-2.0.5.dist-info/METADATA
hcat-2.0.5.dist-info/WHEEL
hcat-2.0.5.dist-info/entry_points.txt
hcat-2.0.5.dist-info/top_level.txt
hcat-2.0.5.dist-info/RECORD
