Metadata-Version: 2.1
Name: hcat
Version: 2.0.5
Requires-Dist: pyside6 (>=6.4.1)
Requires-Dist: torch (>=2.0.0)
Requires-Dist: py-machineid (>=0.2.1)
Requires-Dist: torchvision (>=0.14.1)
Requires-Dist: wget (>=3.2)
Requires-Dist: scikit-image (>=0.19.3)
Requires-Dist: numpy (<2)
Requires-Dist: tqdm (>=4.64.1)
Requires-Dist: yacs (>=0.1.8)
Requires-Dist: numba (>=0.54.0)
Requires-Dist: Cython (>=3.0.0b3)
Requires-Dist: requests
Requires-Dist: imagecodecs
